setup.py
file_kvstore/__init__.py
file_kvstore/constants.py
file_kvstore/io.py
file_kvstore/parser.py
file_kvstore/utils.py
file_kvstore.egg-info/PKG-INFO
file_kvstore.egg-info/SOURCES.txt
file_kvstore.egg-info/dependency_links.txt
file_kvstore.egg-info/entry_points.txt
file_kvstore.egg-info/requires.txt
file_kvstore.egg-info/top_level.txt