Metadata-Version: 1.0
Name: file-kvstore
Version: 0.1.0
Summary: Tool for storing key/value pairs in text files
Home-page: https://github.com/michael-christen/file-kvstore
Author: Michael Christen
Author-email: UNKNOWN
License: MIT
Platform: UNKNOWN
